dev_calc/__init__.py
dev_calc/__main__.py
dev_calc/dev_calc.py
dev_calc-1.0.0.dist-info/LICENSE
dev_calc-1.0.0.dist-info/METADATA
dev_calc-1.0.0.dist-info/WHEEL
dev_calc-1.0.0.dist-info/entry_points.txt
dev_calc-1.0.0.dist-info/top_level.txt
dev_calc-1.0.0.dist-info/RECORD
