Metadata-Version: 2.1
Name: dev_calc
Version: 1.0.0
Summary: A simple calculator package for the command line
Home-page: https://github.com/EUdds/programmers_calculator
Author: Eric Udlis
Author-email: Eric Udlis <udlis.eric@gmail.com>
License: GNU GENERAL PUBLIC LICENSE
Project-URL: Homepage, https://github.com/eudds/programmers_calculator
Keywords: calculator,command line,simple
Classifier: Programming Language :: Python
Classifier: Programming Language :: Python :: 3
Requires-Python: >=3.9
License-File: LICENSE
Provides-Extra: dev
Requires-Dist: black; extra == "dev"
Requires-Dist: bumpver; extra == "dev"
Requires-Dist: isort; extra == "dev"
Requires-Dist: pip-tools; extra == "dev"
